Metadata-Version: 1.1
Name: extquerysets
Version: 0.0.3
Summary: Extended QuerySets for Django
Home-page: https://bitbucket.org/rami_dk/extquerysets
Author: Ramil Aglyautdinov
Author-email: aglyautdinov@gmail.com
License: MIT
Platform: UNKNOWN
Classifier: Programming Language :: Python :: 3
Classifier: License :: OSI Approved :: MIT License
Classifier: Operating System :: OS Independent
